LICENSE
README.md
setup.cfg
setup.py
src/torchvideo/__init__.py
src/torchvideo/__version__.py
src/torchvideo/samplers.py
src/torchvideo/tools.py
src/torchvideo/datasets/__init__.py
src/torchvideo/datasets/gulp_video_dataset.py
src/torchvideo/datasets/helpers.py
src/torchvideo/datasets/image_folder_video_dataset.py
src/torchvideo/datasets/types.py
src/torchvideo/datasets/video_dataset.py
src/torchvideo/datasets/video_folder_dataset.py
src/torchvideo/datasets/label_sets/__init__.py
src/torchvideo/datasets/label_sets/csv_label_set.py
src/torchvideo/datasets/label_sets/dummy_label_set.py
src/torchvideo/datasets/label_sets/gulp_label_set.py
src/torchvideo/datasets/label_sets/label_set.py
src/torchvideo/datasets/label_sets/lambda_label_set.py
src/torchvideo/internal/__init__.py
src/torchvideo/internal/readers.py
src/torchvideo/internal/utils.py
src/torchvideo/transforms/__init__.py
src/torchvideo/transforms/functional/__init__.py
src/torchvideo/transforms/functional/normalize.py
src/torchvideo/transforms/functional/time_to_channel.py
src/torchvideo/transforms/transforms/__init__.py
src/torchvideo/transforms/transforms/center_crop_video.py
src/torchvideo/transforms/transforms/collect_frames.py
src/torchvideo/transforms/transforms/compose.py
src/torchvideo/transforms/transforms/identity_transform.py
src/torchvideo/transforms/transforms/internal.py
src/torchvideo/transforms/transforms/multiscale_crop_video.py
src/torchvideo/transforms/transforms/ndarray_to_pil_video.py
src/torchvideo/transforms/transforms/normalize_video.py
src/torchvideo/transforms/transforms/pil_video_to_tensor.py
src/torchvideo/transforms/transforms/random_crop_video.py
src/torchvideo/transforms/transforms/random_horizontal_flip_video.py
src/torchvideo/transforms/transforms/random_resized_crop_video.py
src/torchvideo/transforms/transforms/resize_video.py
src/torchvideo/transforms/transforms/time_apply.py
src/torchvideo/transforms/transforms/time_to_channel.py
src/torchvideo2.egg-info/PKG-INFO
src/torchvideo2.egg-info/SOURCES.txt
src/torchvideo2.egg-info/dependency_links.txt
src/torchvideo2.egg-info/requires.txt
src/torchvideo2.egg-info/top_level.txt