Metadata-Version: 2.1
Name: torchvideo2
Version: 0.0.3
Summary: PyTorch video dataset library forked from torchvideo
Home-page: https://github.com/DaniNem/torchvideo
Author: Will Price
Author-email: will.price94+torchvideo@gmail.com
License: MPL2+
Platform: UNKNOWN
Classifier: License :: OSI Approved :: Mozilla Public License 2.0 (MPL 2.0)
Classifier: Programming Language :: Python
Classifier: Programming Language :: Python :: 3
Classifier: Programming Language :: Python :: 3.6
Classifier: Programming Language :: Python :: 3.7
Classifier: Programming Language :: Python :: Implementation :: CPython
Requires-Python: >=3.5.0
Provides-Extra: visualisation
Provides-Extra: csv
